LICENSE
MANIFEST.in
README.rst
setup.py
rhcalendar/__init__.py
rhcalendar/locales.py
rhcalendar.egg-info/PKG-INFO
rhcalendar.egg-info/SOURCES.txt
rhcalendar.egg-info/dependency_links.txt
rhcalendar.egg-info/not-zip-safe
rhcalendar.egg-info/requires.txt
rhcalendar.egg-info/top_level.txt