Metadata-Version: 1.1
Name: rhcalendar
Version: 1.1.0
Summary: Red Hat business days calendar
Home-page: https://github.com/ktdreyer/rhcalendar
Author: Ken Dreyer
Author-email: ktdreyer@ktdreyer.com
License: MIT
Keywords: workdays
Platform: UNKNOWN
Classifier: Development Status :: 4 - Beta
Classifier: Intended Audience :: Developers
Classifier: License :: OSI Approved :: MIT License
Classifier: Operating System :: OS Independent
Classifier: Programming Language :: Python :: 2.7
Classifier: Programming Language :: Python :: 3.6
